{
  "id_nortag": "-1596678125",
  "index_page": 0,
  "name_nortag": "Gas Mask",
  "total_img": 6,
  "total_page": 0,
  "hc_lt_alb": "-972981027",
  "hc_lt_data_img": "-826725340",
  "hc_lt_nortag": "-926005588",
  "hc_lt_sptag": "-685135616",
  "lt_alb": [
    {
      "id_alb": "66988",
      "name_alb": "Boy",
      "total_img": 8592
    },
    {
      "id_alb": "68811063",
      "name_alb": "Girls",
      "total_img": 68557
    },
    {
      "id_alb": "109656519",
      "name_alb": "Original 6",
      "total_img": 437
    },
    {
      "id_alb": "1443687921",
      "name_alb": "Original",
      "total_img": 1020
    }
  ],
  "lt_data_img": [
    {
      "hc_lt_id_alb": "1109278061",
      "hc_lt_id_nortag": "1188519506",
      "hc_lt_id_sptag": "",
      "id_img": "Original_533720_crop2608_-1018494030",
      "link_img": "UTb0sGqADnbLiHq9qhRMRkSRiLND0Tk7ctN8tpraiieHoxK9HtLL4pcuEenWG/NUTTlznqBoFcC65aVd1/pNepVy4706IhQgSYlgwrgVRHU=",
      "thumb": "UTb0sGqADnbLiHq9qhRMRkSRiLND0Tk7ctN8tpraiieHoxK9HtLL4pcuEenWG/NU04Rn4eNV9Ib2rndbwAfmNZVy4706IhQgSYlgwrgVRHU=",
      "lt_id_alb": [
        "66988",
        "1443687921"
      ],
      "list_id_nortag": [
        "-1596678125",
        "64280026",
        "2011082565",
        "2070745",
        "2109111"
      ]
    },
    {
      "hc_lt_id_alb": "-566931210",
      "hc_lt_id_nortag": "1231518922",
      "hc_lt_id_sptag": "-531009154",
      "id_img": "Original_946378_crop2608_-765779559",
      "link_img": "UTb0sGqADnbLiHq9qhRMRkSRiLND0Tk7ctN8tpraiicOP9Tpx7V4uaKB11cHBOqULP/H6473FefnhSkkR5dUJ5Vy4706IhQgSYlgwrgVRHU=",
      "thumb": "UTb0sGqADnbLiHq9qhRMRkSRiLND0Tk7ctN8tpraiicOP9Tpx7V4uaKB11cHBOqUFtN3LB7pwgCMSeNzAyISr5Vy4706IhQgSYlgwrgVRHU=",
      "lt_id_alb": [
        "68811063"
      ],
      "list_id_nortag": [
        "-1596678125"
      ],
      "lt_id_sptag": [
        "-154622774",
        "-326078627",
        "1600730941",
        "-369535327",
        "1911583362",
        "635218351"
      ]
    },
    {
      "hc_lt_id_alb": "-365719382",
      "hc_lt_id_nortag": "716712342",
      "hc_lt_id_sptag": "-2132579957",
      "id_img": "Original_845798_crop2608_737320157",
      "link_img": "UTb0sGqADnbLiHq9qhRMRkSRiLND0Tk7ctN8tpraiieSWprQ/k3lC6x5nCXJhHCbqQB2Tf2rG0960KfdtpFiZZVy4706IhQgSYlgwrgVRHU=",
      "thumb": "UTb0sGqADnbLiHq9qhRMRkSRiLND0Tk7ctN8tpraiieSWprQ/k3lC6x5nCXJhHCbkyVlaj1EmAkNvEn81s+2T5Vy4706IhQgSYlgwrgVRHU=",
      "lt_id_alb": [
        "68811063",
        "109656519"
      ],
      "list_id_nortag": [
        "-1596678125",
        "2107205243"
      ],
      "lt_id_sptag": [
        "891390002",
        "-2139213873",
        "-1782893951",
        "-271320563",
        "-143534545",
        "-1783086774",
        "1911583362"
      ]
    },
    {
      "hc_lt_id_alb": "-566931210",
      "hc_lt_id_nortag": "1231518922",
      "hc_lt_id_sptag": "887061138",
      "id_img": "Original_945896_crop2608_-1333297989",
      "link_img": "UTb0sGqADnbLiHq9qhRMRkSRiLND0Tk7ctN8tpraiieneZGUIAKOvbW+SCBMMZRx4A0J9/ngxmG6MNP03SCK/ZVy4706IhQgSYlgwrgVRHU=",
      "thumb": "UTb0sGqADnbLiHq9qhRMRkSRiLND0Tk7ctN8tpraiieneZGUIAKOvbW+SCBMMZRxJbKh3c1lib5plf4RApmOVZVy4706IhQgSYlgwrgVRHU=",
      "lt_id_alb": [
        "68811063"
      ],
      "list_id_nortag": [
        "-1596678125"
      ],
      "lt_id_sptag": [
        "-154622774",
        "1429721863",
        "-2139213873",
        "-143380300",
        "1129122964",
        "-271320563",
        "1911583362"
      ]
    },
    {
      "hc_lt_id_alb": "1626877832",
      "hc_lt_id_nortag": "1231518922",
      "hc_lt_id_sptag": "",
      "id_img": "Original_836348_crop2608_2019119068",
      "link_img": "UTb0sGqADnbLiHq9qhRMRkSRiLND0Tk7ctN8tpraiieB3zmXt6KdAWQbeeKbg9JfRVZ7cDbe4OiGYBY5gNesZ5Vy4706IhQgSYlgwrgVRHU=",
      "thumb": "UTb0sGqADnbLiHq9qhRMRkSRiLND0Tk7ctN8tpraiieB3zmXt6KdAWQbeeKbg9JfAHjl9vSXjT8s7yxp+7Kn05Vy4706IhQgSYlgwrgVRHU=",
      "lt_id_alb": [
        "66988",
        "109656519"
      ],
      "list_id_nortag": [
        "-1596678125"
      ]
    },
    {
      "hc_lt_id_alb": "-883319153",
      "hc_lt_id_nortag": "1231518922",
      "hc_lt_id_sptag": "1081486919",
      "id_img": "Original_702271_crop2608_-193159277",
      "link_img": "UTb0sGqADnbLiHq9qhRMRkSRiLND0Tk7ctN8tpraiien+MwQZKvUGUf9dr0Xi1L5cPTO6wgXnfyaJKfPZaYdhpVy4706IhQgSYlgwrgVRHU=",
      "thumb": "UTb0sGqADnbLiHq9qhRMRkSRiLND0Tk7ctN8tpraiien+MwQZKvUGUf9dr0Xi1L5gpoTYJC4ieBQdmFM1T1bwZVy4706IhQgSYlgwrgVRHU=",
      "lt_id_alb": [
        "68811063",
        "1443687921"
      ],
      "list_id_nortag": [
        "-1596678125"
      ],
      "lt_id_sptag": [
        "-14067806",
        "-1811357781",
        "-2139213873",
        "1211227273",
        "-271320563"
      ]
    }
  ],
  "lt_nortag": [
    {
      "id_nortag": "2070745",
      "name_nortag": "Bird",
      "total_img": 95
    },
    {
      "id_nortag": "64280026",
      "name_nortag": "Blood",
      "total_img": 37
    },
    {
      "id_nortag": "2011082565",
      "name_nortag": "Camera",
      "total_img": 19
    },
    {
      "id_nortag": "2109111",
      "name_nortag": "Crow",
      "total_img": 5
    },
    {
      "id_nortag": "2107205243",
      "name_nortag": "Flower",
      "total_img": 497
    },
    {
      "id_nortag": "-1596678125",
      "name_nortag": "Gas Mask",
      "total_img": 6
    }
  ],
  "lt_sptag": [
    {
      "id_sptag": "1600730941",
      "key_sptag": "isGirlCuteCool",
      "name_sptag": "Girls Cute Cool",
      "total": 31431
    },
    {
      "id_sptag": "-1783086774",
      "key_sptag": "isGirlEyesBlackAnime",
      "name_sptag": "Girls Eyes Black",
      "total": 5810
    },
    {
      "id_sptag": "635218351",
      "key_sptag": "isGirlEyesBlueAnime",
      "name_sptag": "Girls Eyes Blue",
      "total": 25656
    },
    {
      "id_sptag": "-1782893951",
      "key_sptag": "isGirlEyesBrownAnime",
      "name_sptag": "Girls Eyes Brown",
      "total": 9376
    },
    {
      "id_sptag": "1129122964",
      "key_sptag": "isGirlEyesVioletAnime",
      "name_sptag": "Girls Eyes Violet",
      "total": 6410
    },
    {
      "id_sptag": "1211227273",
      "key_sptag": "isGirlEyesYellowAnime",
      "name_sptag": "Girls Eyes Yellow",
      "total": 6605
    },
    {
      "id_sptag": "-271320563",
      "key_sptag": "isGirlFaceMasksAnime",
      "name_sptag": "Girls Face Masks",
      "total": 1618
    },
    {
      "id_sptag": "-154622774",
      "key_sptag": "isGirlHairBlackAnime",
      "name_sptag": "Girls Hair Black",
      "total": 16737
    },
    {
      "id_sptag": "-143534545",
      "key_sptag": "isGirlHairBlueAnime",
      "name_sptag": "Girls Hair Blue",
      "total": 9528
    },
    {
      "id_sptag": "-143380300",
      "key_sptag": "isGirlHairGreyAnime",
      "name_sptag": "Girls Hair Grey",
      "total": 9239
    },
    {
      "id_sptag": "-14067806",
      "key_sptag": "isGirlHairSilverAnime",
      "name_sptag": "Girls Hair Silver",
      "total": 16300
    },
    {
      "id_sptag": "-369535327",
      "key_sptag": "isGirlHatsAnime",
      "name_sptag": "Girls Hats",
      "total": 11965
    },
    {
      "id_sptag": "1429721863",
      "key_sptag": "isGirlHornsAnime",
      "name_sptag": "Girls Horns",
      "total": 2031
    },
    {
      "id_sptag": "-326078627",
      "key_sptag": "isGirlLongHairAnime",
      "name_sptag": "Girls Long Hair",
      "total": 47407
    },
    {
      "id_sptag": "-2139213873",
      "key_sptag": "isGirlShortHairAnime",
      "name_sptag": "Girls Short Hair",
      "total": 23769
    },
    {
      "id_sptag": "891390002",
      "key_sptag": "isGirlStudentAnime",
      "name_sptag": "Girls Student",
      "total": 16308
    },
    {
      "id_sptag": "1911583362",
      "key_sptag": "isGirlTieBowsAnime",
      "name_sptag": "Girls Tie Bows",
      "total": 61257
    },
    {
      "id_sptag": "-1811357781",
      "key_sptag": "isGirlUniformAnime",
      "name_sptag": "Girls Uniform",
      "total": 16929
    }
  ]
}